smolt-0.2.dist-info/METADATA
smolt-0.2.dist-info/WHEEL
smolt-0.2.dist-info/entry_points.txt
smolt/__init__.py
smolt/cli.py
smolt/gdb.py
smolt/include/smolt.h
smolt/itm.py
smolt/meta.py
smolt-0.2.dist-info/RECORD
