Metadata-Version: 2.1
Name: smolt
Version: 0.2
Summary: Small minimal-overhead logging toolkit
Author-Email: Vegard Storheil Eriksen <zyp@jvnv.net>
License: MIT
Requires-Python: >=3.10
Requires-Dist: click>=8.1.7
Requires-Dist: pyelftools>=0.31
Requires-Dist: python-orbuculum<0.1,>=0.0.1
Requires-Dist: cpp-symbol-parser<0.2,>=0.1.1
